loggate-1.14.0.dist-info/METADATA
loggate-1.14.0.dist-info/WHEEL
loggate-1.14.0.dist-info/entry_points.txt
loggate-1.14.0.dist-info/licenses/LICENSE
loggate/__init__.py
loggate/filters.py
loggate/formatters.py
loggate/http/__init__.py
loggate/http/aio_api_call.py
loggate/http/simple_api_call.py
loggate/logger.py
loggate/loki/__init__.py
loggate/loki/confirmation_queue.py
loggate/loki/emitters.py
loggate/loki/formatters.py
loggate/loki/handlers.py
loggate-1.14.0.dist-info/RECORD
