Metadata-Version: 2.1
Name: loggate
Version: 1.14.0
Summary: The advance logging system.
Keywords: log,loggin,loggate,logger,loki
Author-Email: Martin Korbel <mkorbel@alps.cz>
License: MIT
Classifier: Topic :: System :: Networking
Classifier: Topic :: Software Development :: Libraries :: Python Modules
Project-URL: homepage, https://github.com/calcite/loggate
Project-URL: repository, https://github.com/calcite/loggate
Project-URL: documentation, https://github.com/calcite/loggate
Requires-Python: <4.0,>=3.9
Provides-Extra: dev
Requires-Dist: pytest>=6.2.5; extra == "dev"
Requires-Dist: PyYAML<7.0,>=5.4.1; extra == "dev"
Requires-Dist: pytest-asyncio; extra == "dev"
Provides-Extra: asyncio
Requires-Dist: aiohttp; extra == "asyncio"
